Box2D/Box2D.py
Box2D/_Box2D.pyd
Box2D/__init__.py
Box2D/b2/__init__.py
Box2D/examples/__init__.py
Box2D/examples/apply_force.py
Box2D/examples/body_types.py
Box2D/examples/box_cutter.py
Box2D/examples/breakable.py
Box2D/examples/bridge.py
Box2D/examples/bullet.py
Box2D/examples/cantilever.py
Box2D/examples/car.py
Box2D/examples/chain.py
Box2D/examples/character_collision.py
Box2D/examples/cloth.py
Box2D/examples/collision_filtering.py
Box2D/examples/collision_processing.py
Box2D/examples/confined.py
Box2D/examples/convex_hull.py
Box2D/examples/conveyor_belt.py
Box2D/examples/distance.py
Box2D/examples/edge_shapes.py
Box2D/examples/edge_test.py
Box2D/examples/empty.py
Box2D/examples/framework.py
Box2D/examples/gish_tribute.py
Box2D/examples/hello.py
Box2D/examples/liquid.py
Box2D/examples/mobile.py
Box2D/examples/motor_joint.py
Box2D/examples/one_sided_platform.py
Box2D/examples/pinball.py
Box2D/examples/pulley.py
Box2D/examples/pyramid.py
Box2D/examples/raycast.py
Box2D/examples/restitution.py
Box2D/examples/rope.py
Box2D/examples/settings.py
Box2D/examples/simple_cv.py
Box2D/examples/theo_jansen.py
Box2D/examples/tiles.py
Box2D/examples/time_of_impact.py
Box2D/examples/top_down_car.py
Box2D/examples/tumbler.py
Box2D/examples/vertical_stack.py
Box2D/examples/web.py
Box2D/examples/backends/__init__.py
Box2D/examples/backends/opencv_draw.py
Box2D/examples/backends/opencv_framework.py
Box2D/examples/backends/pygame_framework.py
Box2D/examples/backends/pygame_gui.py
Box2D/examples/backends/pyglet_framework.py
Box2D/examples/backends/pyqt4_framework.py
Box2D/examples/backends/pyqt4_gui.py
Box2D/examples/backends/pyqt4_gui.ui
Box2D/examples/backends/simple_framework.py
Box2D/examples/data/themes/default/Vera.ttf
Box2D/examples/data/themes/default/box.down.png
Box2D/examples/data/themes/default/box.hover.png
Box2D/examples/data/themes/default/box.normal.png
Box2D/examples/data/themes/default/box.xcf
Box2D/examples/data/themes/default/button.down.tga
Box2D-2.3.10.dist-info/LICENSE
Box2D-2.3.10.dist-info/METADATA
Box2D-2.3.10.dist-info/WHEEL
Box2D-2.3.10.dist-info/top_level.txt
Box2D-2.3.10.dist-info/RECORD
