Metadata-Version: 2.1
Name: Box2D
Version: 2.3.10
Summary: Python Box2D
Home-page: http://github.com/pybox2d/pybox2d
Author: Ken Lauer
Author-email: sirkne@gmail.com
License: zlib
Platform: UNKNOWN
